structure_features/__init__.py
structure_features/loss/__init__.py
structure_features/loss/_factory.py
structure_features/loss/representative_anchor.py
structure_features/loss/residual_anchor_identity.py
structure_features/model/__init__.py
structure_features/model/_base.py
structure_features/model/_factory.py
structure_features/model/simple_structure.py
structure_features/model/simple_structure_raw.py
structure_features/structure_analysis/__init__.py
structure_features/structure_analysis/feature_cluster_visualization.py
structure_features/structure_analysis/feature_difference.py
structure_features/structure_analysis/noncontiguous_structure.py
structure_features/structure_analysis/structure_related_frequency.py
structure_features/structure_extraction/__init__.py
structure_features/structure_extraction/first_index_anchor_residual.py
structure_features/structure_extraction/l1_threshold_graph.py
structure_features/submodule_sampling/__init__.py
structure_features/submodule_sampling/layer_token_sampling.py
structure_features/transform_features/__init__.py
structure_features/transform_features/group_rank.py
structure_features/transform_features/raw.py
structure_features/utils/__init__.py
structure_features/utils/_factory.py
structure_features/utils/_helper.py
structure_features/utils/_registry.py
structure_features-0.1.0.dist-info/licenses/LICENSE
structure_features-0.1.0.dist-info/METADATA
structure_features-0.1.0.dist-info/WHEEL
structure_features-0.1.0.dist-info/top_level.txt
structure_features-0.1.0.dist-info/RECORD
