Metadata-Version: 2.4
Name: structure-features
Version: 0.1.0
Summary: Structuring Hidden Features via Clustering of Unit-Level Activation
Author: Sejik Park
License:                                  Apache License
Project-URL: Paper, https://openreview.net/forum?id=zgNQGoqKS4
Project-URL: Source, https://github.com/Sejik/structure-features
Requires-Python: >=3.11
License-File: LICENSE
Requires-Dist: torch>=2.8
Requires-Dist: torchvision
Requires-Dist: scipy
Requires-Dist: opencv-python
Requires-Dist: pandas
Requires-Dist: grad-cam
Provides-Extra: dev
Requires-Dist: build; extra == "dev"
Requires-Dist: twine; extra == "dev"
Requires-Dist: mkdocs; extra == "dev"
Requires-Dist: mkdocstrings[python]; extra == "dev"
Requires-Dist: mkdocs-material; extra == "dev"
Requires-Dist: mkdocs-gen-files; extra == "dev"
Requires-Dist: mkdocs-literate-nav; extra == "dev"
Requires-Dist: mkdocs-section-index; extra == "dev"
Requires-Dist: pytest; extra == "dev"
Requires-Dist: pytest-benchmark; extra == "dev"
Requires-Dist: pytest-timeout; extra == "dev"
Dynamic: license-file
